{
  "camera": {
    "type": "ortho",
    "keyframer": [
      {
        "time": 0.0,
        "easing": "cubic-in-out",
        "magnitude": 720.0
      }
    ]
  },
  "objects": [
    {
      "time": 0.0,
      "type": "svg",
      "assets": [
        "svg/prelude/*.svg"
      ],
      "repetitions": {
        "count": 4,
        "interval": 1.0
      },
      "keyframer": [
        {
          "asset-index": "rep",
          "time": 0.0,
          "easing": "cubic-in-out",
          "stroke-r": 1.0,
          "stroke-g": 0.0,
          "stroke-b": 0.0,
          "stroke-a": 1.0,
          "c0": 0.0,
          "c1": 0.0,
          "x": 0.0,
          "y": 0.0,
          "z": 0.0,
          "rz": 0.0,
          "scale": 1.0
        },
        {
          "time": 1.0,
          "c0": 0.0,
          "c1": 1.0
        },
        {
          "time": 2.0,
          "easing": "cubic-in-out",
          "scale": 1.0
        },
        {
          "time": 2.0,
          "c0": 1.0,
          "c1": 1.0,
          "stroke-r": 1.0,
          "stroke-g": 0.5,
          "stroke-b": 0.0,
          "stroke-a": 1.0
        }
      ]
    }
  ]
}